quanttide_devops/__init__.py
quanttide_devops/__main__.py
quanttide_devops/artifacts/__init__.py
quanttide_devops/artifacts/pypi.py
quanttide_devops/cli.py
quanttide_devops/config.py
quanttide_devops/repositories/__init__.py
quanttide_devops/repositories/provider.py
quanttide_devops/repositories/repo.py
quanttide_devops-0.1.0b1.dist-info/LICENSE
quanttide_devops-0.1.0b1.dist-info/METADATA
quanttide_devops-0.1.0b1.dist-info/WHEEL
quanttide_devops-0.1.0b1.dist-info/entry_points.txt
quanttide_devops-0.1.0b1.dist-info/RECORD
